README.md
setup.py
alex2.egg-info/PKG-INFO
alex2.egg-info/SOURCES.txt
alex2.egg-info/dependency_links.txt
alex2.egg-info/entry_points.txt
alex2.egg-info/namespace_packages.txt
alex2.egg-info/requires.txt
alex2.egg-info/top_level.txt
orangecontrib/__init__.py
orangecontrib/dev_workflow_alex/__init__.py
orangecontrib/dev_workflow_alex/widgets/Chatbot.py
orangecontrib/dev_workflow_alex/widgets/MetManagement.py
orangecontrib/dev_workflow_alex/widgets/VarManagement.py
orangecontrib/dev_workflow_alex/widgets/WrapMessageBox.py
orangecontrib/dev_workflow_alex/widgets/__init__.py
orangecontrib/dev_workflow_alex/widgets/goto.py
orangecontrib/dev_workflow_alex/widgets/orange_sub_workflow.py
orangecontrib/dev_workflow_alex/widgets/shared_functions.py
orangecontrib/dev_workflow_alex/widgets/shared_variables.py
orangecontrib/dev_workflow_alex/widgets/subworkflow_input.py
orangecontrib/dev_workflow_alex/widgets/subworkflow_output.py